ctk_utils/__init__.py
ctk_utils-0.0.1.dist-info/METADATA
ctk_utils-0.0.1.dist-info/WHEEL
ctk_utils-0.0.1.dist-info/top_level.txt
ctk_utils-0.0.1.dist-info/RECORD
