Metadata-Version: 2.4
Name: ctk-utils
Version: 0.0.1
Summary: 7 Segment Displays for Customtkinter
Author-email: NumbersTada <tadaktatak61@gmail.com>
Classifier: Programming Language :: Python :: 3
Classifier: Operating System :: OS Independent
Classifier: License :: OSI Approved :: MIT License
Requires-Python: >=3.6
Requires-Dist: customtkinter
